advtrain/__init__.py
advtrain/boundary_visualization.py
advtrain/framework.py
advtrain/instantiate_model.py
advtrain/load_dataset.py
advtrain/attack_framework/__init__.py
advtrain/attack_framework/attacks.py
advtrain/attack_framework/multi_lib_attacks.py
advtrain/models/AlexNet.py
advtrain/models/__init__.py
advtrain/models/lenet5.py
advtrain/models/resnet.py
advtrain/models/vgg.py
advtrain/utils/__init__.py
advtrain/utils/normalize.py
advtrain/utils/preprocess.py
advtrain/utils/quant_dorefa.py
advtrain/utils/quantise.py
advtrain/utils/str2bool.py
advtrain/utils/tinyimagenet.py
advtrain-0.0.2.dist-info/LICENSE
advtrain-0.0.2.dist-info/METADATA
advtrain-0.0.2.dist-info/WHEEL
advtrain-0.0.2.dist-info/top_level.txt
advtrain-0.0.2.dist-info/RECORD
