Metadata-Version: 2.1
Name: advtrain
Version: 0.0.2
Summary: ADV-TRAIN is Deep Vision TRaining And INference framework
Home-page: https://github.com/DeepakTatachar/ADV-TRAIN
Author: Deepak Tatachar, Sangamesh Kodge
Author-email: dravikum@purdue.edu
License: UNKNOWN
Platform: UNKNOWN
Classifier: Programming Language :: Python :: 3
Classifier: License :: OSI Approved :: GNU General Public License v3 (GPLv3)
Classifier: Operating System :: OS Independent
Requires-Python: >=3.6
